fintechff_indicator/__init__.py
fintechff_indicator/brokers/TradingView.py
fintechff_indicator/brokers/__init__.py
fintechff_indicator/feeds/MyFeed.py
fintechff_indicator/feeds/MyFeed2.py
fintechff_indicator/feeds/MyLiveFeed.py
fintechff_indicator/feeds/TestFeed.py
fintechff_indicator/feeds/__init__.py
fintechff_indicator/indicators/LongTermDirection.py
fintechff_indicator/indicators/ShortTermDirection.py
fintechff_indicator/indicators/TradeAction.py
fintechff_indicator/indicators/__init__.py
fintechff_indicator-1.1.0.dist-info/LICENSE
fintechff_indicator-1.1.0.dist-info/METADATA
fintechff_indicator-1.1.0.dist-info/WHEEL
fintechff_indicator-1.1.0.dist-info/top_level.txt
fintechff_indicator-1.1.0.dist-info/RECORD
