Metadata-Version: 2.1
Name: fintechff_indicator
Version: 1.1.0
Summary: A python package for providing fintech indicators
Home-page: https://github.com/lihuapinghust/fintechff_indicator
Author: Jonathan Lee
Author-email: lihuapinghust@gmail.com
Classifier: Programming Language :: Python :: 3
Classifier: License :: OSI Approved :: MIT License
Classifier: Operating System :: OS Independent
Requires-Python: >=3.6
License-File: LICENSE
Requires-Dist: backtrader
Requires-Dist: matplotlib
